<?xml version="1.0"?>
<?xml-stylesheet type="text/xsl" href="meta.xsl"?>
<PROJECT><DEVICES><struct_t name="Ngk128" adr="5" info="06.08.2025 9:28:26  NGK128.3.1 BOOTEEP Charger Accel" chip="6" serial="1" SupportUartSpeed="250" NoPowerDataCount="9"><struct_t size="41" WRK="" offset="0" global="0"><uint8_t tip="10" name="автомат" metr="AU" offset="0" global="0">0</uint8_t><int32_t tip="32" name="время" metr="WT" offset="1" global="1">0</int32_t><struct_t name="charge" size="24" offset="5" global="5"><uint8_t tip="10" name="status" readonly="" offset="0" global="5">0</uint8_t><float tip="34" name="Израсходованная_емкость" color="2130706687" eu="Ah" digits="10" precision="7" offset="1" global="6">0</float><float tip="34" name="Оставшаяся_емкость" color="2130706687" eu="Ah" readonly="" digits="5" precision="2" offset="5" global="10">0</float><uint8_t tip="10" name="Ресурс" readonly="" color="2130706687" eu="%" offset="9" global="14">0</uint8_t><uint16_t tip="20" name="Осталось_часов" readonly="" color="2130706687" eu="h" offset="10" global="15">0</uint16_t><float tip="34" name="Температура" color="2132803328" eu="C" readonly="" digits="5" precision="1" offset="12" global="17">0</float><float tip="34" name="Напряжение_батареи" readonly="" eu="V" digits="5" precision="2" offset="16" global="21">0</float><float tip="34" name="Ток" readonly="" eu="mA" digits="5" precision="1" offset="20" global="25">0</float></struct_t><struct_t name="accel" metr="CLA1" size="6" offset="29" global="29"><int16_t tip="22" name="X" offset="0" global="29">0</int16_t><int16_t tip="22" name="Y" offset="2" global="31">0</int16_t><int16_t tip="22" name="Z" offset="4" global="33">0</int16_t></struct_t><struct_t name="ННК" metr="NGK128" size="6" offset="35" global="35"><uint16_t tip="20" name="мз" offset="0" global="35">0</uint16_t><uint16_t tip="20" name="бз" offset="2" global="37">0</uint16_t><uint16_t tip="20" name="нгк" offset="4" global="39">0</uint16_t></struct_t></struct_t><struct_t size="40" RamSize="256" RAM="" offset="0" global="0"><int32_t tip="32" name="время" metr="WT" offset="0" global="0">0</int32_t><struct_t name="charge" size="24" offset="4" global="4"><uint8_t tip="10" name="status" readonly="" offset="0" global="4">0</uint8_t><float tip="34" name="Израсходованная_емкость" color="2130706687" eu="Ah" digits="10" precision="7" offset="1" global="5">0</float><float tip="34" name="Оставшаяся_емкость" color="2130706687" eu="Ah" readonly="" digits="5" precision="2" offset="5" global="9">0</float><uint8_t tip="10" name="Ресурс" readonly="" color="2130706687" eu="%" offset="9" global="13">0</uint8_t><uint16_t tip="20" name="Осталось_часов" readonly="" color="2130706687" eu="h" offset="10" global="14">0</uint16_t><float tip="34" name="Температура" color="2132803328" eu="C" readonly="" digits="5" precision="1" offset="12" global="16">0</float><float tip="34" name="Напряжение_батареи" readonly="" eu="V" digits="5" precision="2" offset="16" global="20">0</float><float tip="34" name="Ток" readonly="" eu="mA" digits="5" precision="1" offset="20" global="24">0</float></struct_t><struct_t name="accel" metr="CLA1" size="6" offset="28" global="28"><int16_t tip="22" name="X" offset="0" global="28">0</int16_t><int16_t tip="22" name="Y" offset="2" global="30">0</int16_t><int16_t tip="22" name="Z" offset="4" global="32">0</int16_t></struct_t><struct_t name="ННК" metr="NGK128" size="6" offset="34" global="34"><uint16_t tip="20" name="мз" offset="0" global="34">0</uint16_t><uint16_t tip="20" name="бз" offset="2" global="36">0</uint16_t><uint16_t tip="20" name="нгк" offset="4" global="38">0</uint16_t></struct_t></struct_t><struct_t size="56" EEP="" offset="0" global="0"><struct_t size="1" name="Смена_батареи" from="0" offset="0" global="0"><uint8_t tip="10" name="Флаг_смены_батареи_1" offset="0" global="0">0</uint8_t></struct_t><struct_t size="4" name="Объём_батареи" from="8" password="BAT" offset="1" global="1"><float tip="34" name="Ёмкость_батареи" color="2130706687" eu="Ah" offset="0" global="1">0</float></struct_t><struct_t size="12" name="errors" from="16" password="rwelgrtgh" offset="5" global="5"><struct_t size="8" name="ResetErr" offset="0" global="5"><uint16_t tip="20" name="ResetCount" readonly="" offset="0" global="5">0</uint16_t><uint8_t tip="10" name="ResetFunction" readonly="" offset="2" global="7">0</uint8_t><uint8_t tip="10" name="ResetRegister" readonly="" offset="3" global="8">0</uint8_t><int32_t tip="32" name="восстановленый_кадр" metr="WT" readonly="" offset="4" global="9">0</int32_t></struct_t><int32_t tip="32" name="время_qzErr" metr="WT" readonly="" offset="8" global="13">0</int32_t></struct_t><struct_t size="29" name="сохраненное_состояние" from="512" password="Reset_BAT_enable" offset="17" global="17"><struct_t size="5" name="состояние_и_кадр" offset="0" global="17"><uint8_t tip="10" name="автомат" metr="AU" readonly="" offset="0" global="17">0</uint8_t><int32_t tip="32" name="время" metr="WT" readonly="" offset="1" global="18">0</int32_t></struct_t><struct_t name="Разряд_батареи" size="24" offset="5" global="22"><uint8_t tip="10" name="status" readonly="" offset="0" global="22">0</uint8_t><float tip="34" name="Израсходованная_емкость" color="2130706687" eu="Ah" digits="10" precision="7" offset="1" global="23">0</float><float tip="34" name="Оставшаяся_емкость" color="2130706687" eu="Ah" readonly="" digits="5" precision="2" offset="5" global="27">0</float><uint8_t tip="10" name="Ресурс" readonly="" color="2130706687" eu="%" offset="9" global="31">0</uint8_t><uint16_t tip="20" name="Осталось_часов" readonly="" color="2130706687" eu="h" offset="10" global="32">0</uint16_t><float tip="34" name="Температура" color="2132803328" eu="C" readonly="" digits="5" precision="1" offset="12" global="34">0</float><float tip="34" name="Напряжение_батареи" readonly="" eu="V" digits="5" precision="2" offset="16" global="38">0</float><float tip="34" name="Ток" readonly="" eu="mA" digits="5" precision="1" offset="20" global="42">0</float></struct_t></struct_t><struct_t size="10" name="Настройка_DAC" from="1024" password="DAC" offset="46" global="46"><struct_t eu="mV" size="6" name="dac" offset="0" global="46"><uint16_t tip="20" name="мз" eu="mV" offset="0" global="46">0</uint16_t><uint16_t tip="20" name="бз" eu="mV" offset="2" global="48">0</uint16_t><uint16_t tip="20" name="нгк" color="16711680" eu="mV" offset="4" global="50">0</uint16_t></struct_t><struct_t size="4" name="ГК" offset="6" global="52"><float tip="34" name="kGK" digits="10" precision="5" offset="0" global="52">0</float></struct_t></struct_t></struct_t></struct_t></DEVICES></PROJECT>
